{"formations_arduino_arduino-code.md":"OVp8mWYc","formations_arduino_arduino-ex1.md":"DR3Z1j5S","formations_arduino_arduino-ex2.md":"DTqIO_YN","formations_arduino_arduino-ex3.md":"8Hz7AsAE","formations_arduino_arduino-ressources.md":"CUylYKIS","formations_arduino_arduino.md":"CxGArZta","formations_esp32_esp32-arduino.md":"CF93h6SP","formations_esp32_esp32-exemple.md":"CcAk8IpI","formations_esp32_esp32-intro.md":"BmNeJs8u","formations_esp32_esp32-platformio.md":"DCQsvL4O","formations_esp32_esp32-projet.md":"vUfkSrL-","formations_esp32_esp32-wifi.md":"cehFAy2M","index.md":"WPPR_UlQ","projets_assos_avenir.md":"DuxNNIew","projets_avenir.md":"DROFITf7"}
